Metadata-Version: 2.1
Name: hdeps
Version: 1.4.0
Summary: Simple what-if dep resolution for python
Home-page: https://github.com/hdeps/hdeps/
Author: Tim Hatch
Author-email: tim@timhatch.com
License: MIT
Requires-Python: >=3.10
License-File: LICENSE
Requires-Dist: appdirs
Requires-Dist: cachecontrol[filecache]
Requires-Dist: click
Requires-Dist: keke
Requires-Dist: metadata-please >=0.1.0
Requires-Dist: pypi-simple
Requires-Dist: requests
Requires-Dist: seekablehttpfile
Requires-Dist: indexurl
Requires-Dist: packaging
Requires-Dist: vmodule
Provides-Extra: dev
Requires-Dist: black ==23.12.1 ; extra == 'dev'
Requires-Dist: checkdeps ==0.9.0 ; extra == 'dev'
Requires-Dist: flake8 ==7.0.0 ; extra == 'dev'
Requires-Dist: mypy ==1.8.0 ; extra == 'dev'
Requires-Dist: tox ==4.12.1 ; extra == 'dev'
Requires-Dist: twine ==4.0.2 ; extra == 'dev'
Requires-Dist: ufmt ==2.3.0 ; extra == 'dev'
Requires-Dist: usort ==1.0.7 ; extra == 'dev'
Requires-Dist: wheel ==0.42.0 ; extra == 'dev'
Provides-Extra: test
Requires-Dist: coverage >=6 ; extra == 'test'
Requires-Dist: parameterized ; extra == 'test'
